Workbook

Sheet sales-data
A1: ID | B1: Order Order Date | C1: Customer Name | D1: Salesperson | E1: Region | F1: State | G1: Category | H1: Product | I1: Quantity | J1: Unit Price | K1: Discount % | L1: Cost Price | M1: Payment Mode | N1: Customer Type | O1: Gross sales | P1: Discount Amount | Q1: Net sales | R1: Total cost | S1: Profit | T1: Profit margin% | U1: Month | V1: Year | W1: Profit status
A2: ORD001 | B2: 46025 | C2: Rahul Sharma | D2: Amit | E2: North | F2: Rajasthan | G2: Electronics | H2: Wireless Mouse | I2: 3 | J2: 800 | K2: 0.05 | L2: 500 | M2: UPI | N2: New | O2: =I2*J2 -> 2400 | P2: =O2*K2 -> 120 | Q2: =O2-P2 -> 2280 | R2: =I2*L2 -> 1500 | S2: =Q2-R2 -> 780 | T2: =IF(Q2=0,0,S2/Q2) -> 0.34210526 | U2: =TEXT(B2,"MMM") -> Jan | V2: =YEAR(B2) -> 2026 | W2: =IF(S2>0,"Profit","Loss") -> Profit
A3: ORD002 | B3: 46027 | C3: Priya Singh | D3: Neha | E3: West | F3: Gujarat | G3: Furniture | H3: Office Chair | I3: 2 | J3: 6500 | K3: 0.1 | L3: 4300 | M3: Card | N3: Existing | O3: =I3*J3 -> 13000 | P3: =O3*K3 -> 1300 | Q3: =O3-P3 -> 11700 | R3: =I3*L3 -> 8600 | S3: =Q3-R3 -> 3100 | T3: =IF(Q3=0,0,S3/Q3) -> 0.26495726 | U3: =TEXT(B3,"MMM") -> Jan | V3: =YEAR(B3) -> 2026 | W3: =IF(S3>0,"Profit","Loss") -> Profit
A4: ORD003 | B4: 46030 | C4: Mohit Jain | D4: Raj | E4: North | F4: Delhi | G4: Electronics | H4: Keyboard | I4: 5 | J4: 1200 | K4: 0.05 | L4: 700 | M4: Cash | N4: New | O4: =I4*J4 -> 6000 | P4: =O4*K4 -> 300 | Q4: =O4-P4 -> 5700 | R4: =I4*L4 -> 3500 | S4: =Q4-R4 -> 2200 | T4: =IF(Q4=0,0,S4/Q4) -> 0.38596491 | U4: =TEXT(B4,"MMM") -> Jan | V4: =YEAR(B4) -> 2026 | W4: =IF(S4>0,"Profit","Loss") -> Profit
A5: ORD004 | B5: 46034 | C5: Sneha Verma | D5: Amit | E5: South | F5: Karnataka | G5: Clothing | H5: Formal Shirt | I5: 4 | J5: 1800 | K5: 0.08 | L5: 1100 | M5: UPI | N5: Existing | O5: =I5*J5 -> 7200 | P5: =O5*K5 -> 576 | Q5: =O5-P5 -> 6624 | R5: =I5*L5 -> 4400 | S5: =Q5-R5 -> 2224 | T5: =IF(Q5=0,0,S5/Q5) -> 0.33574879 | U5: =TEXT(B5,"MMM") -> Jan | V5: =YEAR(B5) -> 2026 | W5: =IF(S5>0,"Profit","Loss") -> Profit
A6: ORD005 | B6: 46037 | C6: Arjun Mehta | D6: Pooja | E6: West | F6: Maharashtra | G6: Electronics | H6: Headphones | I6: 3 | J6: 2500 | K6: 0.12 | L6: 1600 | M6: Card | N6: New | O6: =I6*J6 -> 7500 | P6: =O6*K6 -> 900 | Q6: =O6-P6 -> 6600 | R6: =I6*L6 -> 4800 | S6: =Q6-R6 -> 1800 | T6: =IF(Q6=0,0,S6/Q6) -> 0.27272727 | U6: =TEXT(B6,"MMM") -> Jan | V6: =YEAR(B6) -> 2026 | W6: =IF(S6>0,"Profit","Loss") -> Profit
A7: ORD006 | B7: 46042 | C7: Kavita Joshi | D7: Neha | E7: East | F7: West Bengal | G7: Furniture | H7: Study Table | I7: 2 | J7: 7500 | K7: 0.07 | L7: 5000 | M7: Bank | N7: Existing | O7: =I7*J7 -> 15000 | P7: =O7*K7 -> 1050 | Q7: =O7-P7 -> 13950 | R7: =I7*L7 -> 10000 | S7: =Q7-R7 -> 3950 | T7: =IF(Q7=0,0,S7/Q7) -> 0.28315412 | U7: =TEXT(B7,"MMM") -> Jan | V7: =YEAR(B7) -> 2026 | W7: =IF(S7>0,"Profit","Loss") -> Profit
A8: ORD007 | B8: 46046 | C8: Rohit Gupta | D8: Raj | E8: North | F8: Haryana | G8: Clothing | H8: Jeans | I8: 6 | J8: 2200 | K8: 0.1 | L8: 1400 | M8: UPI | N8: New | O8: =I8*J8 -> 13200 | P8: =O8*K8 -> 1320 | Q8: =O8-P8 -> 11880 | R8: =I8*L8 -> 8400 | S8: =Q8-R8 -> 3480 | T8: =IF(Q8=0,0,S8/Q8) -> 0.29292929 | U8: =TEXT(B8,"MMM") -> Jan | V8: =YEAR(B8) -> 2026 | W8: =IF(S8>0,"Profit","Loss") -> Profit
A9: ORD008 | B9: 46055 | C9: Anjali Agarwal | D9: Amit | E9: West | F9: Rajasthan | G9: Electronics | H9: Bluetooth Speaker | I9: 4 | J9: 3200 | K9: 0.05 | L9: 2100 | M9: Card | N9: Existing | O9: =I9*J9 -> 12800 | P9: =O9*K9 -> 640 | Q9: =O9-P9 -> 12160 | R9: =I9*L9 -> 8400 | S9: =Q9-R9 -> 3760 | T9: =IF(Q9=0,0,S9/Q9) -> 0.30921053 | U9: =TEXT(B9,"MMM") -> Feb | V9: =YEAR(B9) -> 2026 | W9: =IF(S9>0,"Profit","Loss") -> Profit
A10: ORD009 | B10: 46059 | C10: Vivek Yadav | D10: Pooja | E10: South | F10: Tamil Nadu | G10: Furniture | H10: Bookshelf | I10: 2 | J10: 5500 | K10: 0.1 | L10: 3600 | M10: Cash | N10: New | O10: =I10*J10 -> 11000 | P10: =O10*K10 -> 1100 | Q10: =O10-P10 -> 9900 | R10: =I10*L10 -> 7200 | S10: =Q10-R10 -> 2700 | T10: =IF(Q10=0,0,S10/Q10) -> 0.27272727 | U10: =TEXT(B10,"MMM") -> Feb | V10: =YEAR(B10) -> 2026 | W10: =IF(S10>0,"Profit","Loss") -> Profit
A11: ORD010 | B11: 46063 | C11: Neha Kapoor | D11: Neha | E11: East | F11: Bihar | G11: Clothing | H11: Jacket | I11: 3 | J11: 3500 | K11: 0.15 | L11: 2200 | M11: UPI | N11: Existing | O11: =I11*J11 -> 10500 | P11: =O11*K11 -> 1575 | Q11: =O11-P11 -> 8925 | R11: =I11*L11 -> 6600 | S11: =Q11-R11 -> 2325 | T11: =IF(Q11=0,0,S11/Q11) -> 0.2605042 | U11: =TEXT(B11,"MMM") -> Feb | V11: =YEAR(B11) -> 2026 | W11: =IF(S11>0,"Profit","Loss") -> Profit
A12: ORD011 | B12: 46067 | C12: Manish Saini | D12: Raj | E12: North | F12: Rajasthan | G12: Electronics | H12: Smart Watch | I12: 2 | J12: 6000 | K12: 0.08 | L12: 3900 | M12: Card | N12: New | O12: =I12*J12 -> 12000 | P12: =O12*K12 -> 960 | Q12: =O12-P12 -> 11040 | R12: =I12*L12 -> 7800 | S12: =Q12-R12 -> 3240 | T12: =IF(Q12=0,0,S12/Q12) -> 0.29347826 | U12: =TEXT(B12,"MMM") -> Feb | V12: =YEAR(B12) -> 2026 | W12: =IF(S12>0,"Profit","Loss") -> Profit
A13: ORD012 | B13: 46071 | C13: Pankaj Gupta | D13: Pooja | E13: West | F13: Gujarat | G13: Furniture | H13: Sofa Chair | I13: 2 | J13: 9000 | K13: 0.12 | L13: 6000 | M13: Bank | N13: Existing | O13: =I13*J13 -> 18000 | P13: =O13*K13 -> 2160 | Q13: =O13-P13 -> 15840 | R13: =I13*L13 -> 12000 | S13: =Q13-R13 -> 3840 | T13: =IF(Q13=0,0,S13/Q13) -> 0.24242424 | U13: =TEXT(B13,"MMM") -> Feb | V13: =YEAR(B13) -> 2026 | W13: =IF(S13>0,"Profit","Loss") -> Profit
... A31: ORD030 | B31: 46163 | C31: Isha Mehta | D31: Neha | E31: West | F31: Rajasthan | G31: Electronics | H31: Printer | I31: 2 | J31: 11000 | K31: 0.05 | L31: 7200 | M31: UPI | N31: Existing | O31: =I31*J31 -> 22000 | P31: =O31*K31 -> 1100 | Q31: =O31-P31 -> 20900 | R31: =I31*L31 -> 14400 | S31: =Q31-R31 -> 6500 | T31: =IF(Q31=0,0,S31/Q31) -> 0.31100478 | U31: =TEXT(B31,"MMM") -> May | V31: =YEAR(B31) -> 2026 | W31: =IF(S31>0,"Profit","Loss") -> Profit

Sheet KPI Dashboard
A1: KPI | B1: Formula
A2: Total sales | B2: =SUM('sales-data'!Q1:Q984) -> 454090
A3: Total profit | B3: =SUM('sales-data'!S1:S984) -> 126390
A4: Total orders | B4: =COUNTA('sales-data'!A1:A31) -> 31
A5: Units sold | B5: =SUM('sales-data'!I2:I984) -> 107
A6: Average order value | B6: =SUM('sales-data'!Q2)/COUNTA('sales-data'!A2:A984) -> 76
A7: Total Discount | B7: =SUM('sales-data'!P5:P984) -> 43790
A8: Profit Margin | B8: =SUM('sales-data'!S5:S984)/SUM('sales-data'!Q5:Q984) -> 0.27695035
A9: Profitable Orders | B9: =COUNTIF('sales-data'!W5:W984,"Profit") -> 27
A14: Region | B14: orders | C14: sales | D14: Profit
A15: North | B15: =COUNTIF('sales-data'!E2:E984,A15) -> 9 | C15: =SUMIF('sales-data'!E2:E984,A15,'sales-data'!Q2:Q984) -> 110235 | D15: =SUMIF('sales-data'!E2:E984,A15,'sales-data'!S2:S984) -> 33335
A16: South | B16: =COUNTIF('sales-data'!E3:E984,A16) -> 6 | C16: =SUMIF('sales-data'!E3:E984,A16,'sales-data'!Q3:Q984) -> 60164 | D16: =SUMIF('sales-data'!E3:E984,A16,'sales-data'!S3:S984) -> 17964
A17: East | B17: =COUNTIF('sales-data'!E4:E984,A17) -> 6 | C17: =SUMIF('sales-data'!E4:E984,A17,'sales-data'!Q4:Q984) -> 105351 | D17: =SUMIF('sales-data'!E4:E984,A17,'sales-data'!S4:S984) -> 28551
A18: West | B18: =COUNTIF('sales-data'!E5:E984,A18) -> 8 | C18: =SUMIF('sales-data'!E5:E984,A18,'sales-data'!Q5:Q984) -> 166640 | D18: =SUMIF('sales-data'!E5:E984,A18,'sales-data'!S5:S984) -> 43440
A28: Category | B28: Orders | C28: sales | D28: Profit | E28: Average sales
A29: Electronics | B29: =COUNTIF('sales-data'!G2:G984,A29) -> 13 | C29: =SUMIF('sales-data'!G2:G984,A29,'sales-data'!Q2:Q984) -> 231241 | D29: =SUMIF('sales-data'!G2:G984,A29,'sales-data'!S2:S984) -> 63741 | E29: =AVERAGEIF('sales-data'!G2:G984,A29,'sales-data'!Q2:Q984) -> 17787.769
A30: Furniture | B30: =COUNTIF('sales-data'!G3:G984,A30) -> 9 | C30: =SUMIF('sales-data'!G3:G984,A30,'sales-data'!Q3:Q984) -> 143138 | D30: =SUMIF('sales-data'!G3:G984,A30,'sales-data'!S3:S984) -> 39238 | E30: =AVERAGEIF('sales-data'!G3:G984,A30,'sales-data'!Q3:Q984) -> 15904.222
A31: Clothing | B31: =COUNTIF('sales-data'!G4:G984,A31) -> 8 | C31: =SUMIF('sales-data'!G4:G984,A31,'sales-data'!Q4:Q984) -> 79711 | D31: =SUMIF('sales-data'!G4:G984,A31,'sales-data'!S4:S984) -> 23411 | E31: =AVERAGEIF('sales-data'!G4:G984,A31,'sales-data'!Q4:Q984) -> 9963.875
A38: Salesperson | B38: Orders | C38: Sales | D38: Profit
A39: Amit | B39: =COUNTIF('sales-data'!D2:D984,A39) -> 8 | C39: =SUMIF('sales-data'!D2:D984,A39,'sales-data'!Q2:Q984) -> 88999 | D39: =SUMIF('sales-data'!D2:D984,A39,'sales-data'!S2:S984) -> 27099
A40: Neha | B40: =COUNTIF('sales-data'!D3:D984,A40) -> 8 | C40: =SUMIF('sales-data'!D3:D984,A40,'sales-data'!Q3:Q984) -> 122251 | D40: =SUMIF('sales-data'!D3:D984,A40,'sales-data'!S3:S984) -> 35551
A41: Raj | B41: =COUNTIF('sales-data'!D4:D984,A41) -> 7 | C41: =SUMIF('sales-data'!D4:D984,A41,'sales-data'!Q4:Q984) -> 83660 | D41: =SUMIF('sales-data'!D4:D984,A41,'sales-data'!S4:S984) -> 25260
A42: Pooja | B42: =COUNTIF('sales-data'!D5:D984,A42) -> 7 | C42: =SUMIF('sales-data'!D5:D984,A42,'sales-data'!Q5:Q984) -> 159180 | D42: =SUMIF('sales-data'!D5:D984,A42,'sales-data'!S5:S984) -> 38480
A45: Customer Type | B45: Orders | C45: Sales | D45: Profit
A46: New | B46: =COUNTIF('sales-data'!N2:N984,A46) -> 15 | C46: =SUMIF('sales-data'!N2:N984,A46,'sales-data'!Q2:Q984) -> 170375 | D46: =SUMIF('sales-data'!N2:N984,A46,'sales-data'!S2:S984) -> 50875
A47: Existing | B47: =COUNTIF('sales-data'!N3:N984,A47) -> 15 | C47: =SUMIF('sales-data'!N3:N984,A47,'sales-data'!Q3:Q984) -> 283715 | D47: =SUMIF('sales-data'!N3:N984,A47,'sales-data'!S3:S984) -> 75515
A51: Payment Mode | B51: Orders | C51: Sales
A52: UPI | B52: =COUNTIF('sales-data'!M2:M984,A52) -> 10 | C52: =SUMIF('sales-data'!M2:M984,A52,'sales-data'!Q2:Q984) -> 140399
A53: Card | B53: =COUNTIF('sales-data'!M3:M984,A53) -> 9 | C53: =SUMIF('sales-data'!M3:M984,A53,'sales-data'!Q3:Q984) -> 150163
A54: Cash | B54: =COUNTIF('sales-data'!M4:M984,A54) -> 6 | C54: =SUMIF('sales-data'!M4:M984,A54,'sales-data'!Q4:Q984) -> 68748
A55: Bank | B55: =COUNTIF('sales-data'!M5:M984,A55) -> 5 | C55: =SUMIF('sales-data'!M5:M984,A55,'sales-data'!Q5:Q984) -> 94780
A59: Month | B59: Sales | C59: Profit
A60: Jan | B60: =SUMIF('sales-data'!U2:U984,A60,'sales-data'!Q2:Q984) -> 58734 | C60: =SUMIF('sales-data'!U2:U984,A60,'sales-data'!S2:S984) -> 17534
A61: Feb | B61: =SUMIF('sales-data'!U3:U984,A61,'sales-data'!Q3:Q984) -> 80605 | C61: =SUMIF('sales-data'!U3:U984,A61,'sales-data'!S3:S984) -> 23005
A62: Mar | B62: =SUMIF('sales-data'!U4:U984,A62,'sales-data'!Q4:Q984) -> 120936 | C62: =SUMIF('sales-data'!U4:U984,A62,'sales-data'!S4:S984) -> 32136
A63: Apr | B63: =SUMIF('sales-data'!U5:U984,A63,'sales-data'!Q5:Q984) -> 98217 | C63: =SUMIF('sales-data'!U5:U984,A63,'sales-data'!S5:S984) -> 28717
A64: May | B64: =SUMIF('sales-data'!U6:U984,A64,'sales-data'!Q6:Q984) -> 95598 | C64: =SUMIF('sales-data'!U6:U984,A64,'sales-data'!S6:S984) -> 24998

Sheet Sales Dashboard
A1: SALES PERFORMANCE DASHBOARD
B4: TOTAL SALES | D4: TOTAL PROFIT | F4: ORDERS | H4: UNITS SOLD | J4: AOV
B6: =SUM('sales-data'!Q2:Q1000) -> 454090 | D6: =SUM('sales-data'!S2:S1000) -> 126390 | F6: =COUNTA('sales-data'!A2:A1000) -> 30 | H6: =SUM('sales-data'!I1:I1000) -> 107 | J6: =AVERAGE('sales-data'!Q2:Q1000) -> 15136.333
